cccs_yara-2.8.dist-info/licenses/LICENSE
yara_validator/CCCS_YARA.yml
yara_validator/CCCS_YARA_values.yml
yara_validator/README.md
yara_validator/__init__.py
yara_validator/cli.py
yara_validator/constants.py
yara_validator/validator.py
yara_validator/validator_cfg.yml
yara_validator/validator_functions.py
yara_validator/yara_file_processor.py
yara_validator/stix2_patch/__init__.py
yara_validator/stix2_patch/filter_casefold.py
cccs_yara-2.8.dist-info/METADATA
cccs_yara-2.8.dist-info/WHEEL
cccs_yara-2.8.dist-info/entry_points.txt
cccs_yara-2.8.dist-info/top_level.txt
cccs_yara-2.8.dist-info/RECORD
