Metadata-Version: 2.4
Name: cccs-yara
Version: 2.8
Summary: A CCCS utility for YARA rule metadata validation
License-File: LICENSE
Requires-Dist: clint>=0.5.1
Requires-Dist: GitPython>=3.1.0
Requires-Dist: packaging>=19.0
Requires-Dist: plyara
Requires-Dist: python-baseconv>=1.2.2
Requires-Dist: PyYAML>=5.1
Requires-Dist: stix2>=2.1.0
Requires-Dist: yara-python>=4.0.2
Dynamic: description
Dynamic: description-content-type
Dynamic: license-file
Dynamic: requires-dist
Dynamic: summary
